{
	"transubstantiationalist": 1,
	"overintellectualization": 1,
	"philosophicopsychological": 1,
	"polytetrafluoroethylene": 1,
	"scientificophilosophical": 1,
	"magnetothermoelectricity": 1,
	"anthropomorphologically": 1,
	"scientificogeographical": 1,
	"cyclotrimethylenetrinitramine": 1,
	"tetraiodophenolphthalein": 1,
	"thymolsulphonephthalein": 1,
	"electrophotomicrography": 1,
	"regeneratoryregeneratress": 1,
	"microspectrophotometrically": 1,
	"pseudolamellibranchiate": 1,
	"pathologicopsychological": 1,
	"hydroxydesoxycorticosterone": 1,
	"antidisestablishmentarianism": 1,
	"microspectrophotometric": 1,
	"dihdroxycholecalciferol": 1,
	"disestablismentarianism": 1,
	"antidisestablishmentarian": 1,
	"formaldehydesulphoxylate": 1,
	"electrocardiographically": 1,
	"disestablishmentarianism": 1,
	"diphenylaminechlorarsine": 1,
	"pseudophilanthropically": 1,
	"gastroenteroanastomosis": 1,
	"magnetohydrodynamically": 1,
	"phenolsulphonephthalein": 1,
	"hematospectrophotometer": 1,
	"overindividualistically": 1,
	"demethylchlortetracycline": 1,
	"formaldehydesulphoxylic": 1,
	"pancreaticoduodenostomy": 1,
	"immunoelectrophoretically": 1,
	"preobtrudingpreobtrusion": 1,
	"dichlorodifluoromethane": 1,
	"pseudointernationalistic": 1,
	"electroencephalographical": 1,
	"chlorotrifluoroethylene": 1,
	"thyroparathyroidectomize": 1,
	"desoxyribonucleoprotein": 1,
	"pseudolamellibranchiata": 1,
	"philosophicotheological": 1,
	"microspectrophotometrical": 1,
	"pericardiomediastinitis": 1,
	"blepharosphincterectomy": 1,
	"superincomprehensibleness": 1,
	"epididymodeferentectomy": 1,
	"microelectrophoretically": 1,
	"electroencephalographic": 1,
	"preinferredpreinferring": 1,
	"hydroxydehydrocorticosterone": 1,
	"trinitrophenylmethylnitramine": 1,
	"macracanthrorhynchiasis": 1,
	"dichlorodiphenyltrichloroethane": 1,
	"electroencephalographically": 1,
	"pathologicohistological": 1
}